README.md
libcfbf.py
setup.py
libcfbf.egg-info/PKG-INFO
libcfbf.egg-info/SOURCES.txt
libcfbf.egg-info/dependency_links.txt
libcfbf.egg-info/top_level.txt