Metadata-Version: 2.1
Name: libcfbf
Version: 0.4
Summary: An implementation of Microsoft's Compound File Binary Format
Home-page: https://git.rcarz.net/bobc/libcfbf
Author: Bob Carroll
Author-email: bob.carroll@alum.rit.edu
License: UNKNOWN
Platform: UNKNOWN
Classifier: Development Status :: 4 - Beta
Classifier: Intended Audience :: Developers
Classifier: License :: OSI Approved :: GNU General Public License v2 (GPLv2)
Classifier: Operating System :: OS Independent
Classifier: Programming Language :: Python :: 3
Classifier: Topic :: Office/Business :: Office Suites
Classifier: Topic :: Software Development :: Libraries
